image_serve-0.1.3.dist-info/licenses/LICENSE
imgserve/__init__.py
imgserve/app.py
imgserve/cli.py
imgserve/renderer.py
image_serve-0.1.3.dist-info/METADATA
image_serve-0.1.3.dist-info/WHEEL
image_serve-0.1.3.dist-info/entry_points.txt
image_serve-0.1.3.dist-info/top_level.txt
image_serve-0.1.3.dist-info/RECORD
