Metadata-Version: 2.4
Name: image-serve
Version: 0.1.3
Summary: Serve images from current directory or JSON index as a web gallery
Author-email: Daniel Bowen <daniel@chestnut-software.com>
License: MIT
Project-URL: Homepage, https://github.com/dnielbowen/image-serve
Project-URL: Repository, https://github.com/dnielbowen/image-serve
Project-URL: Issues, https://github.com/dnielbowen/image-serve/issues
Classifier: Development Status :: 4 - Beta
Classifier: Intended Audience :: End Users/Desktop
Classifier: License :: OSI Approved :: MIT License
Classifier: Programming Language :: Python :: 3
Classifier: Programming Language :: Python :: 3.8
Classifier: Programming Language :: Python :: 3.9
Classifier: Programming Language :: Python :: 3.10
Classifier: Programming Language :: Python :: 3.11
Classifier: Programming Language :: Python :: 3.12
Classifier: Topic :: Internet :: WWW/HTTP :: HTTP Servers
Requires-Python: >=3.8
License-File: LICENSE
Requires-Dist: flask>=3.0.0
Requires-Dist: waitress>=3.0.0
Dynamic: license-file
